{
  "parent": "",
  "path": "CovenantChoice",
  "name": "CovenantChoice",
  "type": "directory",
  "children": [
    {
      "parent": "CovenantChoice",
      "path": "CovenantChoice\\CovenantChoiceCelebration.PNG",
      "name": "CovenantChoiceCelebration.PNG",
      "type": "file"
    },
    {
      "parent": "CovenantChoice",
      "path": "CovenantChoice\\CovenantChoiceOfferingsKyrian.PNG",
      "name": "CovenantChoiceOfferingsKyrian.PNG",
      "type": "file"
    },
    {
      "parent": "CovenantChoice",
      "path": "CovenantChoice\\CovenantChoiceOfferingsNecrolords.PNG",
      "name": "CovenantChoiceOfferingsNecrolords.PNG",
      "type": "file"
    },
    {
      "parent": "CovenantChoice",
      "path": "CovenantChoice\\CovenantChoiceOfferingsNightFae.PNG",
      "name": "CovenantChoiceOfferingsNightFae.PNG",
      "type": "file"
    },
    {
      "parent": "CovenantChoice",
      "path": "CovenantChoice\\CovenantChoiceOfferingsVenthyr.PNG",
      "name": "CovenantChoiceOfferingsVenthyr.PNG",
      "type": "file"
    },
    {
      "parent": "CovenantChoice",
      "path": "CovenantChoice\\CovenantChoiceScrollingBackgroundKyrian.PNG",
      "name": "CovenantChoiceScrollingBackgroundKyrian.PNG",
      "type": "file"
    },
    {
      "parent": "CovenantChoice",
      "path": "CovenantChoice\\CovenantChoiceScrollingBackgroundNecrolords.PNG",
      "name": "CovenantChoiceScrollingBackgroundNecrolords.PNG",
      "type": "file"
    },
    {
      "parent": "CovenantChoice",
      "path": "CovenantChoice\\CovenantChoiceScrollingBackgroundNightFae.PNG",
      "name": "CovenantChoiceScrollingBackgroundNightFae.PNG",
      "type": "file"
    },
    {
      "parent": "CovenantChoice",
      "path": "CovenantChoice\\CovenantChoiceScrollingBackgroundVenthyr.PNG",
      "name": "CovenantChoiceScrollingBackgroundVenthyr.PNG",
      "type": "file"
    },
    {
      "parent": "CovenantChoice",
      "path": "CovenantChoice\\CovenantChoiceUI.PNG",
      "name": "CovenantChoiceUI.PNG",
      "type": "file"
    },
    {
      "parent": "CovenantChoice",
      "path": "CovenantChoice\\CovenantChoiceUIAlphaMask.PNG",
      "name": "CovenantChoiceUIAlphaMask.PNG",
      "type": "file"
    },
    {
      "parent": "CovenantChoice",
      "path": "CovenantChoice\\CovenantChoiceUIMask.PNG",
      "name": "CovenantChoiceUIMask.PNG",
      "type": "file"
    }
  ]
}